ratelimit/__init__.py
ratelimit/config.py
ratelimit/context.py
ratelimit/endpoint.py
ratelimit/error.py
ratelimit/ranking/__init__.py
ratelimit/ranking/base.py
ratelimit/ranking/redis.py
ratelimit/response.py
ratelimit/rule.py
ratelimit/store/__init__.py
ratelimit/store/base.py
ratelimit/store/redis.py
ratelimit/user.py
ratelimit/util.py
ratelimit_fastapi-1.1.3.dist-info/LICENSE
ratelimit_fastapi-1.1.3.dist-info/METADATA
ratelimit_fastapi-1.1.3.dist-info/WHEEL
ratelimit_fastapi-1.1.3.dist-info/RECORD
