Metadata-Version: 2.1
Name: ratelimit-fastapi
Version: 1.1.3
Summary: Ratelimit solution for FastAPI
License: GPL-3.0-only
Author: kuyugama
Author-email: mail.kuyugama@gmail.com
Requires-Python: >=3.9
Classifier: Framework :: FastAPI
Classifier: License :: OSI Approved :: GNU General Public License v3 (GPLv3)
Classifier: Programming Language :: Python :: 3
Classifier: Programming Language :: Python :: 3.9
Classifier: Programming Language :: Python :: 3.10
Classifier: Programming Language :: Python :: 3.11
Classifier: Programming Language :: Python :: 3.12
Provides-Extra: redis
Requires-Dist: fastapi (>=0.115.0)
Requires-Dist: redis[hiredis] (>=5.2.0,<6.0.0) ; extra == "redis"
